trailpack/__init__.py
trailpack/cli.py
trailpack/main.py
trailpack-0.2.0.dist-info/licenses/LICENSE
trailpack-0.2.0.dist-info/METADATA
trailpack-0.2.0.dist-info/WHEEL
trailpack-0.2.0.dist-info/entry_points.txt
trailpack-0.2.0.dist-info/top_level.txt
trailpack-0.2.0.dist-info/RECORD
