Metadata-Version: 2.4
Name: trailpack
Version: 0.2.0
Summary: Contains all the python boilerplate you need to create a Brightway ecosystem package.
Author-email: Brightcon Hackathon Group 1 <hackathon@example.com>
Maintainer-email: Brightcon Hackathon Group 1 <hackathon@example.com>
Project-URL: source, https://github.com/TimoDiepers/trailpaack
Project-URL: homepage, https://github.com/TimoDiepers/trailpaack
Project-URL: tracker, https://github.com/TimoDiepers/trailpaack/issues
Classifier: Development Status :: 4 - Beta
Classifier: Programming Language :: Python
Classifier: Programming Language :: Python :: 3.12
Classifier: Programming Language :: Python :: 3.13
Classifier: Natural Language :: English
Classifier: Operating System :: OS Independent
Classifier: Topic :: Scientific/Engineering
Requires-Python: <3.14,>=3.12
License-File: LICENSE
Requires-Dist: pyst-client
Requires-Dist: langcodes
Requires-Dist: httpx
Requires-Dist: openpyxl
Requires-Dist: streamlit>=1.28.0
Requires-Dist: pandas>=2.0.0
Requires-Dist: polars>=0.20.0
Requires-Dist: pyarrow>=14.0.0
Requires-Dist: python-dotenv
Requires-Dist: typer>=0.9.0
Requires-Dist: rich>=13.0.0
Requires-Dist: pydantic>=2.0.0
Requires-Dist: pyyaml
Provides-Extra: testing
Requires-Dist: trailpack; extra == "testing"
Requires-Dist: pytest; extra == "testing"
Requires-Dist: pytest-cov; extra == "testing"
Requires-Dist: python-coveralls; extra == "testing"
Provides-Extra: dev
Requires-Dist: build; extra == "dev"
Requires-Dist: pre-commit; extra == "dev"
Requires-Dist: pylint; extra == "dev"
Requires-Dist: pytest; extra == "dev"
Requires-Dist: pytest-cov; extra == "dev"
Requires-Dist: pytest-randomly; extra == "dev"
Requires-Dist: setuptools; extra == "dev"
Dynamic: license-file
